{"nodes": [{"id": "improve_live_metrics_design", "label": "Improve Live Metrics Design", "file_type": "document", "source_file": "openspec/changes/archive/2026-05-11-improve-live-metrics-visibility/design.md", "source_location": null, "source_url": null, "captured_at": null, "author": null, "contributor": null}, {"id": "validation_preview_4way", "label": "4-Way Validation Preview Grid", "file_type": "document", "source_file": "openspec/changes/archive/2026-05-11-improve-live-metrics-visibility/design.md", "source_location": "design.md:68-78", "source_url": null, "captured_at": null, "author": null, "contributor": null}, {"id": "split_metric_charts", "label": "Split Metric Charts (Loss/PSNR/SSIM)", "file_type": "document", "source_file": "openspec/changes/archive/2026-05-11-improve-live-metrics-visibility/design.md", "source_location": "design.md:54-58", "source_url": null, "captured_at": null, "author": null, "contributor": null}], "edges": [{"source": "improve_live_metrics_design", "target": "live_metrics_system", "relation": "references", "confidence": "EXTRACTED", "confidence_score": 1.0, "source_file": "openspec/changes/archive/2026-05-11-improve-live-metrics-visibility/design.md", "source_location": "design.md:3-22", "weight": 1.0}, {"source": "improve_live_metrics_design", "target": "split_metric_charts", "relation": "references", "confidence": "EXTRACTED", "confidence_score": 1.0, "source_file": "openspec/changes/archive/2026-05-11-improve-live-metrics-visibility/design.md", "source_location": "design.md:54-58", "weight": 1.0}, {"source": "improve_live_metrics_design", "target": "validation_preview_4way", "relation": "references", "confidence": "EXTRACTED", "confidence_score": 1.0, "source_file": "openspec/changes/archive/2026-05-11-improve-live-metrics-visibility/design.md", "source_location": "design.md:68-78", "weight": 1.0}, {"source": "validation_preview_4way", "target": "live_metrics_system", "relation": "implements", "confidence": "INFERRED", "confidence_score": 0.85, "source_file": "openspec/changes/archive/2026-05-11-improve-live-metrics-visibility/design.md", "source_location": "design.md:68-78", "weight": 1.0}, {"source": "split_metric_charts", "target": "live_metrics_system", "relation": "implements", "confidence": "INFERRED", "confidence_score": 0.85, "source_file": "openspec/changes/archive/2026-05-11-improve-live-metrics-visibility/design.md", "source_location": "design.md:54-58", "weight": 1.0}, {"source": "improve_live_metrics_design", "target": "build_desktop_workflow_tasks", "relation": "references", "confidence": "INFERRED", "confidence_score": 0.75, "source_file": "openspec/changes/archive/2026-05-11-improve-live-metrics-visibility/design.md", "source_location": "design.md:3-4", "weight": 1.0}], "hyperedges": [{"id": "live_metrics_visibility_improvement", "label": "Live Metrics Visibility Improvement Components", "nodes": ["split_metric_charts", "validation_preview_4way", "live_metrics_visibility_spec", "improve_live_metrics_tasks"], "relation": "form", "confidence": "EXTRACTED", "confidence_score": 1.0, "source_file": "openspec/changes/archive/2026-05-11-improve-live-metrics-visibility/design.md"}]}